flydenity/__init__.py
flydenity/__main__.py
flydenity/parser.py
flydenity/processed_itu_countries.csv
flydenity/processed_itu_countries_regex.csv
flydenity/processed_itu_organizations.csv
flydenity/processed_itu_organizations_regex.csv
tests/__init__.py
tests/test_consistency.py
tests/test_parse.py
tests/test_parse_icao24bit.py
flydenity-0.1.6.dist-info/LICENSE.md
flydenity-0.1.6.dist-info/METADATA
flydenity-0.1.6.dist-info/WHEEL
flydenity-0.1.6.dist-info/entry_points.txt
flydenity-0.1.6.dist-info/top_level.txt
flydenity-0.1.6.dist-info/RECORD
