Metadata-Version: 2.1
Name: flydenity
Version: 0.1.6
Summary: Flydenity is an aircraft callsign identification library. Parsers aircraft registration prefix to identify nation of origin
Home-page: https://github.com/Collen-Roller/arp
Author: Collen Roller
Author-email: collen.roller@gmail.com
License: UNKNOWN
Keywords: aircraft,planes,registration,callsign,prefix,aircraft callsign,plane,air
Platform: UNKNOWN
Classifier: Programming Language :: Python :: 3.6
Classifier: Programming Language :: Python :: 3.7
Classifier: License :: OSI Approved :: MIT License
Classifier: Operating System :: OS Independent
Requires-Python: >=3.6
Requires-Dist: python-dotenv (>=0.14.0)
Provides-Extra: dev
Requires-Dist: check-manifest ; extra == 'dev'
